[
    {
        "Key": "page1.1",
        "Speaker": "H肴",
        "WwiseEventID": "",
        "zh_CN": "郎君~你要是不忙的话，和我一起看会儿书怎么样？"
    },
    {
        "Key": "page1.2",
        "Speaker": "H主角",
        "WwiseEventID": "",
        "zh_CN": "行啊，正好我也想午休……"
    },
    {
        "Key": "page1.3",
        "Speaker": "H主角",
        "WwiseEventID": "",
        "zh_CN": "等等，你说的是……看书？"
    },
    {
        "Key": "page1.4",
        "Speaker": "H肴",
        "WwiseEventID": "",
        "zh_CN": "干嘛一副很惊讶的表情，我不能偶尔看看书吗？"
    },
    {
        "Key": "page1.5",
        "Speaker": "H主角",
        "WwiseEventID": "",
        "zh_CN": "当然行，那你打算看什么书？"
    },
    {
        "Key": "page1.6",
        "Speaker": "H肴",
        "WwiseEventID": "",
        "zh_CN": "嗯……我准备了《秘戏图考》、《胜蓬莱》，还有什么……花营……什么的……"
    },
    {
        "Key": "page1.7",
        "Speaker": "H主角",
        "WwiseEventID": "",
        "zh_CN": "听上去都是朔州的古书啊。"
    },
    {
        "Key": "page1.8",
        "Speaker": "H肴",
        "WwiseEventID": "",
        "zh_CN": "是啊，朔州那边有这么个说法，把这些书放在房里偶尔翻阅，恒约后的日子就会更加幸福。"
    },
    {
        "Key": "page1.9",
        "Speaker": "H肴",
        "WwiseEventID": "",
        "zh_CN": "我这不是想着和郎君一起试试~"
    },
    {
        "Key": "page1.10",
        "Speaker": "H主角",
        "WwiseEventID": "",
        "zh_CN": "（嗯？这些书该不会是……）"
    },
    {
        "Key": "page1.11",
        "Speaker": "H肴",
        "WwiseEventID": "",
        "zh_CN": "嘿~郎君，我们从哪本开始？"
    },
    {
        "Key": "choice01",
        "Speaker": "",
        "WwiseEventID": "",
        "zh_CN": "《秘戏图考》"
    },
    {
        "Key": "choice02",
        "Speaker": "",
        "WwiseEventID": "",
        "zh_CN": "《胜蓬莱》"
    },
    {
        "Key": "page2.1",
        "Speaker": "H肴",
        "WwiseEventID": "",
        "zh_CN": "那就这本了！"
    },
    {
        "Key": "page2.2",
        "Speaker": "",
        "WwiseEventID": "",
        "zh_CN": "肴翻开了这本书……"
    },
    {
        "Key": "page2.3",
        "Speaker": "",
        "WwiseEventID": "",
        "zh_CN": "朔州软笔勾出灵动的眷侣，正琴瑟和鸣，好不畅快。"
    },
    {
        "Key": "page2.4",
        "Speaker": "H肴",
        "WwiseEventID": "",
        "zh_CN": "等等，这里面是……"
    },
    {
        "Key": "page2.5",
        "Speaker": "H肴",
        "WwiseEventID": "",
        "zh_CN": "郎君……要继续看下去吗？"
    },
    {
        "Key": "page2.6",
        "Speaker": "H主角",
        "WwiseEventID": "",
        "zh_CN": "继续吧，毕竟对我们以后的生活大有帮助啊。"
    }
]